SimpleChat
SimpleChat.egg-info
setup.cfg
setup.py
SimpleChat/Makefile
SimpleChat/README.txt
SimpleChat/SimpleChat.py
SimpleChat/TODO.txt
SimpleChat/__init__.py
SimpleChat/scconfig.py
SimpleChat.egg-info/PKG-INFO
SimpleChat.egg-info/SOURCES.txt
SimpleChat.egg-info/SOURCES.txt~
SimpleChat.egg-info/dependency_links.txt
SimpleChat.egg-info/entry_points.txt
SimpleChat.egg-info/not-zip-safe
SimpleChat.egg-info/top_level.txt
SimpleChat/i18n/SimpleChat-no.po
SimpleChat/skins/simple_chat/jquery.min.js.dtml
SimpleChat/skins/simple_chat/simple_chat_add.pt
SimpleChat/skins/simple_chat/simple_chat_ban.pt
SimpleChat/skins/simple_chat/simple_chat_banned.pt
SimpleChat/skins/simple_chat/simple_chat_index.pt
SimpleChat/skins/simple_chat/simple_chat_logs.pt
SimpleChat/skins/simple_chat/simple_chat_report.pt
SimpleChat/skins/simple_chat/simple_chat_report_submit.pt