Metadata-Version: 1.0
Name: SimpleChat
Version: 1.0dev
Summary: Simple chat (messaging system) for Zope and Zope products such as Silva, Plone etc.
Home-page: http://www.nidelven-it.no/custom/plone/hjemmeside/services/development
Author: Morten W. Petersen
Author-email: morten@nidelven-it.no
License: GPL 2.0
Keywords: zope silva plone messaging chat simple ajax accessible
Platform: UNKNOWN
